LICENSE.txt
MANIFEST.in
README.md
requirements.txt
setup.cfg
setup.py
vext_importer.pth
vext/__init__.py
vext.egg-info/PKG-INFO
vext.egg-info/SOURCES.txt
vext.egg-info/dependency_links.txt
vext.egg-info/entry_points.txt
vext.egg-info/not-zip-safe
vext.egg-info/requires.txt
vext.egg-info/top_level.txt
vext/cmdline/__init__.py
vext/env/__init__.py
vext/gatekeeper/__init__.py
vext/helpers/__init__.py
vext/helpers/sip.py
vext/install/__init__.py
vext/registry/__init__.py