Metadata-Version: 1.1
Name: vext
Version: 0.6.2
Summary: Use system python packages from a virtualenv
Home-page: https://github.com/stuaxo/vext
Author: Stuart Axon
Author-email: stuaxo2@yahoo.com
License: MIT
Keywords: setuptools development
Platform: UNKNOWN
Classifier: Development Status :: 3 - Alpha
Classifier: Intended Audience :: Developers
Classifier: Topic :: Software Development :: Build Tools
Classifier: License :: OSI Approved :: MIT License
Classifier: Programming Language :: Python :: 2.7
Classifier: Programming Language :: Python :: 3.4
